{
  "endpoints":[
    {
      "name":"User Methods",
      "methods":[
        {
          "MethodName":"Show User",
          "Synopsis":"This method allows you to retrieve the user object associated with the given API token",
          "HTTPMethod":"GET",
          "URI":"/users/self",
          "RequiresOAuth":"N",
          "parameters":[]
        },
        {
          "MethodName":"Show User",
          "Synopsis":"This method allows you to retrieve the user object associated with the given API token",
          "HTTPMethod":"GET",
          "URI":"/users/:userid",
          "RequiresOAuth":"N",
          "parameters":[
            {
              "Name":"userid",
              "Required":"Y",
              "Default":"",
              "Type":"string",
              "Description":"The user ID"
            }
          ]
        }
      ]
    }
  ]
}